LICENSE
MANIFEST.in
README.md
setup.py
django_full_url.egg-info/PKG-INFO
django_full_url.egg-info/SOURCES.txt
django_full_url.egg-info/dependency_links.txt
django_full_url.egg-info/requires.txt
django_full_url.egg-info/top_level.txt
full_url/__init__.py
full_url/context_processors.py
full_url/grabber.py