Metadata-Version: 1.1
Name: django-full-url
Version: 0.1
Summary: Small tool for easily getting parts or full URL in Django templates and views.
Home-page: UNKNOWN
Author: R. Moelker
Author-email: UNKNOWN
License: UNKNOWN
Platform: UNKNOWN
Classifier: Environment :: Web Environment
Classifier: Framework :: Django
Classifier: Intended Audience :: Developers
Classifier: License :: OSI Approved :: BSD License
Classifier: Operating System :: OS Independent
Classifier: Programming Language :: Python
Classifier: Programming Language :: Python :: 2.7
Classifier: Topic :: Internet :: WWW/HTTP
